py_eigentrust/__init__.py
py_eigentrust/eigentrust_client.py
py_eigentrust-0.0.1.dist-info/METADATA
py_eigentrust-0.0.1.dist-info/WHEEL
py_eigentrust-0.0.1.dist-info/RECORD
