Metadata-Version: 2.1
Name: py-eigentrust
Version: 0.0.1
Summary: 
Author: SeungJu Lee
Author-email: sj@karma3labs.com
Requires-Python: >=3.10,<4.0
Classifier: Programming Language :: Python :: 3
Classifier: Programming Language :: Python :: 3.10
Classifier: Programming Language :: Python :: 3.11
Classifier: Programming Language :: Python :: 3.12
Requires-Dist: pandas (>=2.2.2,<3.0.0)
Requires-Dist: urllib3 (>=2.2.1,<3.0.0)
